sample_statistics/__init__.py
sample_statistics/main.py
tests/__init__.py
tests/test_main.py
sample_statistics-1.0.1.dist-info/LICENSE
sample_statistics-1.0.1.dist-info/METADATA
sample_statistics-1.0.1.dist-info/WHEEL
sample_statistics-1.0.1.dist-info/top_level.txt
sample_statistics-1.0.1.dist-info/RECORD
