Metadata-Version: 2.1
Name: sample-statistics
Version: 1.0.1
Summary: A package for calculating weighted statistics on a set of samples.
Author: Christos Tegkelidis
Author-email: cteg@kth.se
License-File: LICENSE
Requires-Dist: numpy
Requires-Dist: statsmodels
